featrixsphere/__init__.py
featrixsphere/client.py
featrixsphere/api/__init__.py
featrixsphere/api/api_endpoint.py
featrixsphere/api/client.py
featrixsphere/api/foundational_model.py
featrixsphere/api/http_client.py
featrixsphere/api/notebook_helper.py
featrixsphere/api/prediction_result.py
featrixsphere/api/predictor.py
featrixsphere/api/reference_record.py
featrixsphere/api/vector_database.py
featrixsphere-0.2.6379.dist-info/METADATA
featrixsphere-0.2.6379.dist-info/WHEEL
featrixsphere-0.2.6379.dist-info/entry_points.txt
featrixsphere-0.2.6379.dist-info/top_level.txt
featrixsphere-0.2.6379.dist-info/RECORD
