Metadata-Version: 2.4
Name: featrixsphere
Version: 0.2.6379
Summary: Transform any CSV into a production-ready ML model in minutes, not months.
Home-page: https://github.com/Featrix/sphere
Author: Featrix
Author-email: support@featrix.com
Project-URL: Bug Tracker, https://github.com/Featrix/sphere/issues
Project-URL: Documentation, https://github.com/Featrix/sphere#readme
Project-URL: Source Code, https://github.com/Featrix/sphere
Keywords: machine learning,artificial intelligence,neural networks,embedding spaces,prediction,classification,regression,csv,api,client,featrix,sphere,automl,no-code ml
Classifier: Development Status :: 4 - Beta
Classifier: Intended Audience :: Developers
Classifier: License :: OSI Approved :: MIT License
Classifier: Operating System :: OS Independent
Classifier: Programming Language :: Python :: 3
Classifier: Programming Language :: Python :: 3.8
Classifier: Programming Language :: Python :: 3.9
Classifier: Programming Language :: Python :: 3.10
Classifier: Programming Language :: Python :: 3.11
Classifier: Programming Language :: Python :: 3.12
Classifier: Topic :: Scientific/Engineering :: Artificial Intelligence
Classifier: Topic :: Software Development :: Libraries :: Python Modules
Classifier: Topic :: Internet :: WWW/HTTP :: HTTP Servers
Requires-Python: >=3.8
Requires-Dist: requests>=2.20.0
Requires-Dist: pandas>=1.0.0
Provides-Extra: dev
Requires-Dist: pytest>=6.0; extra == "dev"
Requires-Dist: pytest-cov>=2.0; extra == "dev"
Requires-Dist: black>=21.0; extra == "dev"
Requires-Dist: flake8>=3.8; extra == "dev"
Requires-Dist: mypy>=0.800; extra == "dev"
Provides-Extra: progress
Requires-Dist: rich>=10.0.0; extra == "progress"
Provides-Extra: notebook
Requires-Dist: ipython>=7.0.0; extra == "notebook"
Requires-Dist: ipywidgets>=7.0.0; extra == "notebook"
Provides-Extra: interactive
Requires-Dist: ipywidgets>=7.0.0; extra == "interactive"
Requires-Dist: matplotlib>=3.0.0; extra == "interactive"
Provides-Extra: server
Requires-Dist: fastapi>=0.68.0; extra == "server"
Requires-Dist: uvicorn[standard]>=0.15.0; extra == "server"
Requires-Dist: celery[redis]>=5.0.0; extra == "server"
Requires-Dist: redis>=4.0.0; extra == "server"
Requires-Dist: pydantic-settings>=2.0.0; extra == "server"
Requires-Dist: python-multipart>=0.0.5; extra == "server"
Provides-Extra: ml
Requires-Dist: torch>=1.9.0; extra == "ml"
Requires-Dist: numpy>=1.21.0; extra == "ml"
Requires-Dist: scikit-learn>=1.0.0; extra == "ml"
Requires-Dist: pandas>=1.3.0; extra == "ml"
Provides-Extra: all
Requires-Dist: rich>=10.0.0; extra == "all"
Requires-Dist: ipython>=7.0.0; extra == "all"
Requires-Dist: ipywidgets>=7.0.0; extra == "all"
Requires-Dist: fastapi>=0.68.0; extra == "all"
Requires-Dist: uvicorn[standard]>=0.15.0; extra == "all"
Requires-Dist: celery[redis]>=5.0.0; extra == "all"
Requires-Dist: redis>=4.0.0; extra == "all"
Requires-Dist: pydantic-settings>=2.0.0; extra == "all"
Requires-Dist: python-multipart>=0.0.5; extra == "all"
Requires-Dist: torch>=1.9.0; extra == "all"
Requires-Dist: numpy>=1.21.0; extra == "all"
Requires-Dist: scikit-learn>=1.0.0; extra == "all"
Dynamic: author
Dynamic: author-email
Dynamic: classifier
Dynamic: description
Dynamic: description-content-type
Dynamic: home-page
Dynamic: keywords
Dynamic: project-url
Dynamic: provides-extra
Dynamic: requires-dist
Dynamic: requires-python
Dynamic: summary
